thruster_pulse_command_generator/_cli.py
thruster_pulse_command_generator/command_generator.py
thruster_pulse_command_generator-0.1.0.dist-info/METADATA
thruster_pulse_command_generator-0.1.0.dist-info/WHEEL
thruster_pulse_command_generator-0.1.0.dist-info/entry_points.txt
thruster_pulse_command_generator-0.1.0.dist-info/RECORD
