Metadata-Version: 2.1
Name: thruster-pulse-command-generator
Version: 0.1.0
Summary: 
Author: meoragiusiano
Author-email: meora.giusiano@stellar-exploration.com
Requires-Python: >=3.10,<4.0
Classifier: Programming Language :: Python :: 3
Classifier: Programming Language :: Python :: 3.10
Classifier: Programming Language :: Python :: 3.11
Classifier: Programming Language :: Python :: 3.12
Requires-Dist: openpyxl (>=3.1.5,<4.0.0)
Requires-Dist: pandas (>=2.2.2,<3.0.0)
